{
  "_class": "symbolInstance",
  "do_objectID": "514331A0-05F9-4918-8E73-73A130A284FC",
  "exportOptions": {
    "_class": "exportOptions",
    "exportFormats": [
    ],
    "includedLayerIds": [
    ],
    "layerOptions": 0,
    "shouldTrim": false
  },
  "frame": {
    "_class": "rect",
    "constrainProportions": false,
    "height": 179,
    "width": 884,
    "x": 72,
    "y": 359
  },
  "horizontalSpacing": 0,
  "isFlippedHorizontal": false,
  "isFlippedVertical": false,
  "isLocked": false,
  "isVisible": true,
  "layerListExpandedType": 0,
  "masterInfluenceEdgeMaxXPadding": 0,
  "masterInfluenceEdgeMaxYPadding": 1,
  "masterInfluenceEdgeMinXPadding": 0,
  "masterInfluenceEdgeMinYPadding": 0,
  "name": "Product_Description_Desktop",
  "nameIsFixed": false,
  "overrides": {
    "1EA03CBE-6B9C-4DAA-817B-AC5F4741BF83": "This ice-lolly flavor will transport you to an unstoppable chocolate rain.",
    "A2B03576-495C-4D31-8F95-C3C6B15DBBB7": {
      "symbolID": "2B69D400-23CB-451B-9098-21415F2B66A9"
    }
  },
  "resizingConstraint": 63,
  "resizingType": 0,
  "rotation": 0,
  "shouldBreakMaskChain": false,
  "style": {
    "_class": "style",
    "endDecorationType": 0,
    "miterLimit": 10,
    "startDecorationType": 0
  },
  "symbolID": "5E64CE3C-05BE-4684-AE72-142E4687FC21",
  "userInfo": {
    "com.animaapp.stc-sketch-plugin": {
      "kModelPropertiesKey": {
      }
    }
  },
  "verticalSpacing": 0
}