{
  "_class": "artboard",
  "backgroundColor": {
    "_class": "color",
    "alpha": 1,
    "blue": 1,
    "green": 1,
    "red": 1
  },
  "do_objectID": "0C8B43EB-951A-49E7-8A69-61432D745D7F",
  "exportOptions": {
    "_class": "exportOptions",
    "exportFormats": [
    ],
    "includedLayerIds": [
    ],
    "layerOptions": 0,
    "shouldTrim": false
  },
  "frame": {
    "_class": "rect",
    "constrainProportions": false,
    "height": 850,
    "width": 1280,
    "x": 0,
    "y": 5135
  },
  "hasBackgroundColor": true,
  "hasClickThrough": true,
  "horizontalRulerData": {
    "_class": "rulerData",
    "base": 0,
    "guides": [
    ]
  },
  "includeBackgroundColorInExport": true,
  "includeInCloudUpload": true,
  "isFlippedHorizontal": false,
  "isFlippedVertical": false,
  "isLocked": false,
  "isVisible": true,
  "layerListExpandedType": 2,
  "layers": [
    {
      "class": "symbolInstance",
      "id": "704B9CA1-96E8-483A-9857-256AD0616BC4"
    },
    {
      "class": "symbolInstance",
      "id": "E7A84512-C61B-4988-872B-79D8CEFA2C85"
    },
    {
      "class": "symbolInstance",
      "id": "855A7EE5-DBAE-4DE6-93E3-85AB29B07C6E"
    },
    {
      "class": "symbolInstance",
      "id": "ADAFEA98-937E-415B-8A7E-CF3E1908CAD2"
    },
    {
      "class": "symbolInstance",
      "id": "0C54DAC2-62E5-4805-9914-CF3F1647CFB0"
    },
    {
      "class": "symbolInstance",
      "id": "D2799A7A-75BF-4E5E-97DD-E85C6C095885"
    },
    {
      "class": "symbolInstance",
      "id": "3981D769-1B3B-4479-BDFF-7C09F250F392"
    },
    {
      "class": "symbolInstance",
      "id": "EAC6D64A-6222-4DA8-B947-C5D921506766"
    },
    {
      "class": "symbolInstance",
      "id": "00F1E95B-7AA2-4DA7-AC8D-4B17E62E2E9A"
    },
    {
      "class": "symbolInstance",
      "id": "AEB48915-4503-4C1C-822A-F2E26AA65553"
    }
  ],
  "name": "PDP / Wino forever",
  "nameIsFixed": true,
  "resizesContent": false,
  "resizingConstraint": 63,
  "resizingType": 0,
  "rotation": 0,
  "shouldBreakMaskChain": false,
  "style": {
    "_class": "style",
    "endDecorationType": 0,
    "fills": [
      {
        "_class": "fill",
        "color": {
          "_class": "color",
          "alpha": 1,
          "blue": 1,
          "green": 1,
          "red": 1
        },
        "fillType": 0,
        "isEnabled": true,
        "noiseIndex": 0,
        "noiseIntensity": 0,
        "patternFillType": 1,
        "patternTileScale": 1
      }
    ],
    "miterLimit": 10,
    "startDecorationType": 0
  },
  "userInfo": {
    "com.animaapp.stc-sketch-plugin": {
      "kModelPropertiesKey": {
      }
    }
  },
  "verticalRulerData": {
    "_class": "rulerData",
    "base": 0,
    "guides": [
    ]
  }
}