{
  "_class": "shapePath",
  "booleanOperation": -1,
  "do_objectID": "055F795B-D068-4C6C-BF87-A586FAD2AE17",
  "edited": true,
  "exportOptions": {
    "_class": "exportOptions",
    "exportFormats": [
    ],
    "includedLayerIds": [
    ],
    "layerOptions": 0,
    "shouldTrim": false
  },
  "frame": {
    "_class": "rect",
    "constrainProportions": false,
    "height": 7.272727272727272,
    "width": 19,
    "x": 2.999999999999973,
    "y": 1.818181818181818
  },
  "isClosed": true,
  "isFlippedHorizontal": false,
  "isFlippedVertical": false,
  "isLocked": false,
  "isVisible": true,
  "layerListExpandedType": 0,
  "name": "Path",
  "nameIsFixed": false,
  "pointRadiusBehaviour": 1,
  "points": [
    {
      "_class": "curvePoint",
      "cornerRadius": 0,
      "curveFrom": "{0.99999999999999989, 1}",
      "curveMode": 1,
      "curveTo": "{0.99999999999999989, 1}",
      "hasCurveFrom": false,
      "hasCurveTo": false,
      "point": "{0.99999999999999989, 1}"
    },
    {
      "_class": "curvePoint",
      "cornerRadius": 0,
      "curveFrom": "{1, 9.8686491077791687e-17}",
      "curveMode": 1,
      "curveTo": "{1, 9.8686491077791687e-17}",
      "hasCurveFrom": false,
      "hasCurveTo": false,
      "point": "{1, 9.8686491077791687e-17}"
    },
    {
      "_class": "curvePoint",
      "cornerRadius": 0,
      "curveFrom": "{0.15170970510775089, 0}",
      "curveMode": 1,
      "curveTo": "{0.15170970510775089, 0}",
      "hasCurveFrom": false,
      "hasCurveTo": false,
      "point": "{0.15170970510775089, 0}"
    },
    {
      "_class": "curvePoint",
      "cornerRadius": 0,
      "curveFrom": "{1.0293042690927201e-17, 0.99999999999999978}",
      "curveMode": 1,
      "curveTo": "{1.0293042690927201e-17, 0.99999999999999978}",
      "hasCurveFrom": false,
      "hasCurveTo": false,
      "point": "{1.0293042690927201e-17, 0.99999999999999978}"
    }
  ],
  "resizingConstraint": 63,
  "resizingType": 0,
  "rotation": 0,
  "shouldBreakMaskChain": false,
  "userInfo": {
    "com.animaapp.stc-sketch-plugin": {
      "kModelPropertiesKey": {
      }
    }
  }
}